coretext/A1.txt
coretext/A2.txt
coretext/A3.txt
coretext/A4.txt
coretext/B1.txt
coretext/B2.txt
coretext/B4.txt
coretext/B6.txt
coretext/B7.txt
coretext/__init__.py
coretext/coreio.py
coretext/newfile.txt
coretext/test.py
yagamicore-0.1.1.dist-info/METADATA
yagamicore-0.1.1.dist-info/WHEEL
yagamicore-0.1.1.dist-info/top_level.txt
yagamicore-0.1.1.dist-info/RECORD
