Metadata-Version: 2.1
Name: yagamicore
Version: 0.1.1
Summary: A simple library for handling text files
Home-page: https://github.com/your-username/yagamicore
Author: Anonymous
Author-email: ifYoucanFindMe@gmail.com
